VerificationEmailC/__init__.py
VerificationEmailC/verificationemail.py
VerificationEmailC-0.0.1.dist-info/LICENSE
VerificationEmailC-0.0.1.dist-info/METADATA
VerificationEmailC-0.0.1.dist-info/WHEEL
VerificationEmailC-0.0.1.dist-info/top_level.txt
VerificationEmailC-0.0.1.dist-info/RECORD
